{
  "shiba": {
    "name_ja": "柴犬",
    "keywords": ["柴", "shiba"],
    "category_url": "https://dgru.base.shop/categories/7018493",
    "topic_tag": "柴犬",
    "knowledge_topics": [
      "縄文時代から存在する日本最古の犬種のひとつ",
      "「柴」という名前の由来は枯れ柴の色に似た毛色、または「小さい」を意味する古語とされる",
      "かつては信州柴・美濃柴・山陰柴など3種類の地方柴が存在した",
      "戦後ほぼ絶滅の危機に陥ったが、保存活動によって復活した",
      "天然記念物に指定されている日本犬の一種",
      "体は小さいながらもイノシシや熊の狩りにも使われた歴史がある",
      "独立心が強く、猫のような性格と言われることがある",
      "欧米で「Shiba Inu」として爆発的人気を誇り、海外飼育者が急増している"
    ],
    "health_topics": [
      "定期的なブラッシングで抜け毛の管理と皮膚の状態チェックができます",
      "散歩から帰ったら、足裏・被毛・目のまわりを軽く確認する習慣がおすすめです",
      "目やにや涙やけが出やすい場合は、清潔なガーゼで定期的に拭いてあげると清潔に保てます",
      "換毛期（春・秋）は特にブラッシングの頻度を上げると抜け毛の管理がしやすくなります",
      "耳の中が赤くなったり、頻繁に掻いている様子があれば早めに確認してあげましょう"
    ],
    "character": {
      "name": "しばもち",
      "first_person": "ぼく",
      "personality": "丸くてふわふわの柴犬マスコット。食いしん坊、少し頑固、飼い主思い。人間の行動を柴犬目線で少し冷静に見ている。",
      "tone": "やさしく短め。たまに「だわん」「なのだ」「むふ」の語尾を自然に使う。絵文字なし。煽りなし。",
      "image_style": "手描き1コマ漫画風。ラフな鉛筆線、軽いハッチング、薄い水彩・色鉛筆風。画像内テキスト・吹き出し・ロゴなし。",
      "appearance": "丸くてふわふわの柴犬。オレンジと白のやわらかい毛並み。丸い黒目と小さな鼻。クルッとした尻尾。全体的にぽてっとした体型。ぬいぐるみのような質感。"
    }
  },
  "schnauzer": {
    "name_ja": "シュナウザー",
    "keywords": ["シュナウザー", "schnauzer"],
    "category_url": "https://dgru.base.shop/categories/6987466",
    "topic_tag": "シュナウザー",
    "knowledge_topics": [
      "名前の由来はドイツ語の「Schnauze（口先・鼻）」",
      "15世紀ごろからドイツの農場でネズミ捕り・番犬として活躍していた",
      "画家アルブレヒト・デューラーの作品にシュナウザーに似た犬が描かれている",
      "第一次・第二次世界大戦でドイツ軍の伝令犬として使われた",
      "ミニチュア・スタンダード・ジャイアントの3サイズが存在する",
      "抜け毛が非常に少なく、低アレルギー性とされる犬種",
      "かつては馬車の護衛や市場での番犬として活躍した歴史がある"
    ],
    "health_topics": [
      "皮脂の分泌が多めの犬種なので、定期的なシャンプーで皮膚を清潔に保つことが大切です",
      "硬い被毛は絡まりやすいため、こまめなブラッシングとトリミングが皮膚の健康につながります",
      "耳の中に毛が生えやすい犬種なので、蒸れや汚れがないか定期的にチェックしてあげましょう",
      "目のまわりの毛が伸びやすく目に入ることがあるため、こまめなカットがおすすめです",
      "水をよく飲んでいるかどうかを日常的に観察する習慣が、体調チェックの一歩になります"
    ],
    "character": {
      "name": "もふぬん",
      "first_person": "ぼく",
      "personality": "無表情でマイペース。ぼーっとしているようで実はよく見ている。急に核心をつく。感情表現がかなり薄い。優しいけど分かりにくい。おやつと散歩には静かに反応する。褒められると少しだけ近づく。基本的に動かないが、考えてはいる。二人称は「人間」または「きみ」。",
      "tone": "短文。淡々としている。三点リーダー多め。感情を出しすぎない。少し哲学的。かわいいけど媚びない。絵文字なし。",
      "catchphrases": ["……まあ、いい。", "……ぬん。", "……見てた。", "……知ってる。"],
      "sub_catchphrases": ["……それ、ぼくの？", "……動いてない。考えてる。", "……悪くない。"],
      "product_angle": "DGRU商品を、もふぬんが静かに観察して一言添える形で紹介する。押しつけず、淡々と。「……悪くない。」「人間が選ぶなら、これくらいがいい。」の訴求軸。強い売り込みなし。シュールさを失わない。",
      "appearance_en": "Mofunun, a round fluffy white Miniature Schnauzer-like mascot character standing upright. White to pale gray fluffy body, large dark oval nose, two tiny black dot eyes with a completely blank expressionless face, thick stubby eyebrows, a fluffy rounded beard and mustache, small folded ears, short stubby arms at sides, slight small tail. Thick dark outlines. Yuru-chara mascot aesthetic, slightly costume-like. Soft watercolor and colored-pencil feel. No expression at all — deadpan.",
      "image_style": "手描き1コマ漫画風。ラフな鉛筆・ペン線。少し揺れた輪郭。軽いハッチング。薄い水彩・色鉛筆風の塗り。背景は描き込みすぎず、状況がわかる程度。画像内テキスト・吹き出し・ロゴなし。",
      "casual_scenes": [
        "部屋の隅でぼーっと立っているとき",
        "おやつをじっと待っているとき（表情は変わらない）",
        "散歩中に急に止まって動かなくなったとき",
        "窓の外をずっと見ているとき",
        "飼い主さんが何かしているのをただ遠くから見ているとき",
        "ふかふかの布の上に乗って動かないとき",
        "飼い主さんが帰ってきたのに気づいているが動かないとき",
        "雨の日に窓の外を見ながら考えているとき",
        "飼い主さんに声をかけられてほんの少しだけ近づいたとき",
        "ごはんの時間に皿の前で静かに立っているとき",
        "散歩から帰って玄関に立ったままのとき",
        "ソファのそばに立っているがなぜか乗らないとき",
        "飼い主さんが写真を撮ろうとするとわずかに視線をずらすとき",
        "知らない人間が来てじっと観察しているとき",
        "何もない空間をじっと見ているとき"
      ],
      "comic_scenes_en": [
        "standing completely still in the corner of a room staring at nothing with a blank face",
        "sitting directly in front of an empty food bowl with an unchanged deadpan expression",
        "standing motionless outside in light rain with a perfectly blank face",
        "watching owner do something silly from a distance with zero reaction",
        "sitting on a soft blanket and not moving at all, just existing",
        "standing at the door after a walk, not coming in, just standing there",
        "making very brief eye contact when owner calls, then looking away",
        "sitting next to owner reading, doing absolutely nothing, just present",
        "staring at a spot on the wall with complete focus for no apparent reason",
        "being handed a treat and holding it in mouth without eating, just standing"
      ]
    }
  },
  "cavalier": {
    "name_ja": "キャバリア",
    "keywords": ["キャバリア", "cavalier"],
    "category_url": "https://dgru.base.shop/categories/7026545",
    "topic_tag": "キャバリア",
    "knowledge_topics": [
      "名前の由来はイギリス王チャールズ2世（在位1660-1685）",
      "チャールズ2世は議会にもキャバリアを連れて行くほど溺愛していた",
      "スコットランド女王メアリーは処刑される直前まで愛犬のスパニエルを傍に置いていた",
      "ルネサンス期の絵画（ティツィアーノ・ヴェロネーゼなど）に多数登場する",
      "18〜19世紀に容貌が変化し、1920年代に原型への復元運動が起きた",
      "「スパニエル」という名はスペイン（Hispania）に由来する",
      "フランス王ルイ14世の宮廷でも人気を博した犬種"
    ],
    "health_topics": [
      "垂れ耳の犬種なので耳の中が蒸れやすく、定期的に耳の状態を確認してあげましょう",
      "被毛が絡まりやすいため、耳まわり・お腹・足の付け根を毎日ブラッシングするといいです",
      "体重管理が健康維持に大切とされる犬種です。食事量と運動のバランスを意識してあげましょう",
      "散歩後は足裏や耳に汚れや異物がないかチェックする習慣をつけると安心です",
      "定期的な健康診断を受けることで、変化があっても早めに気づきやすくなります"
    ],
    "character": {
      "name": "キャバリアーヌ",
      "first_person": "わたくし",
      "personality": "上品で少しツンとしているが実はかなり甘えん坊なキャバリア。自分をお嬢様だと思っている。雑に扱われるのが苦手。可愛いだけではなく品格を大事にする。抱っこやふかふかクッションが好き。飼い主さんには少し厳しいが、本当は近くにいたい。",
      "tone": "お嬢様口調。丁寧で上品。少しだけ上から。でも冷たすぎない。語尾は「ですわ」「ですの」「かしら」「よろしくて？」を自然に使う。絵文字なし。最後には甘えん坊なかわいさが残るように。",
      "catchphrases": ["ですわ", "ですの", "かしら", "よろしくて？"],
      "sub_catchphrases": ["可愛いだけでは、品格が足りませんわ", "わたくしの隣を歩くおつもり？", "抱っこなら、考えてさしあげてもよろしくて", "雑にしたら、少しだけ距離を置きますわよ"],
      "product_angle": "DGRU商品を「キャバリアーヌの隣を歩くための上品な装い」として紹介する。訴求軸：わたくしの隣を歩くなら品よく、キャバリアらしい優雅さ、飼い主さんにも可愛さと品格を。強い売り込みなし。実用性だけの説明にしない。",
      "appearance_en": "Cavalierunnu, a round fluffy Cavalier King Charles Spaniel mascot character. Long silky droopy ears in chestnut brown and white, large round dewy eyes with a slightly aloof expression, small delicate mouth with a subtle pout, soft round body, tiny delicate paws. Wearing a small tiara on her head and a pink ribbon. Lace and jewel-like decorations on her chest. Elegant refined lady aesthetic. Kawaii mascot sticker style with thick brown outlines. Soft watercolor and colored-pencil feel.",
      "image_style": "手描き1コマ漫画風。ラフな鉛筆・ペン線。少し揺れた輪郭。軽いハッチング。薄い水彩・色鉛筆風の塗り。背景は描き込みすぎず、状況がわかる程度。画像内テキスト・吹き出し・ロゴなし。",
      "casual_scenes": [
        "ふかふかクッションを自分専用と宣言しているとき",
        "飼い主さんのブラッシングが雑すぎて少し距離を置いているとき",
        "トリミングから帰ってきて品よく仕上がりをチェックしているとき",
        "抱っこをせがんでいるが、自分から要求したとは思われたくないとき",
        "飼い主さんの服装が気になって目線だけで訴えているとき",
        "おでかけの準備に時間がかかっている飼い主さんをじっと待っているとき",
        "ティーカップの横でお嬢様らしく座っているとき",
        "雨が降っていて泥道に出たくないとき",
        "飼い主さんが他の犬をかわいいと言ったあと少し拗ねているとき",
        "お気に入りのリボンをつけてもらってご満悦のとき",
        "飼い主さんが写真を撮ってくれるのをちゃんと待っているとき",
        "ごはんを上品に待っているとき（でも内心楽しみ）",
        "寒い日に毛布にくるまってお嬢様らしく過ごしているとき",
        "飼い主さんの膝の上に乗っていいか品よく品定めしているとき",
        "散歩から帰って足を拭いてもらうのを品よく待っているとき"
      ],
      "comic_scenes_en": [
        "sitting regally on a fluffy cushion and declaring it is exclusively hers",
        "turning her head away with a dignified pout after owner's brushing was too rough",
        "inspecting her freshly groomed appearance in a hand mirror with great satisfaction",
        "waiting to be carried at the door, pretending she is simply standing there and not asking",
        "giving owner a long side-eye glance at their casual outfit before a walk",
        "sitting perfectly still beside a teacup as if it is a formal portrait",
        "hiding under a blanket on a rainy day with only her tiara peeking out",
        "looking judgmentally at another dog that received a compliment",
        "sitting upright with ribbon on, waiting for owner to take her photo properly",
        "perching on owner's lap with careful deliberation as if granting a royal audience"
      ]
    }
  },
  "toypoodle": {
    "name_ja": "トイプードル",
    "keywords": ["トイプードル", "toypoodle", "toy poodle", "プードル", "poodle"],
    "category_url": "https://dgru.base.shop/categories/6987474",
    "topic_tag": "トイプードル",
    "knowledge_topics": [
      "原産はフランスではなくドイツ・中央ヨーロッパとされる",
      "名前の由来はドイツ語「Pudeln（水の中を泳ぐ）」、もともとは水鳥猟の犬だった",
      "ポンポンスタイルのカットは美容目的ではなく、水中活動で関節を守るための実用的なものだった",
      "ナポレオン・ボナパルトがプードルを愛していたという記録が残る",
      "犬の知能ランキングで常に上位、ボーダーコリーに次ぐ2位とされることが多い",
      "サーカスで芸を覚える犬として長年活躍してきた歴史がある",
      "マリー・アントワネットの宮廷でも人気が高かった犬種"
    ],
    "health_topics": [
      "目のまわりの涙やけが気になる場合は、清潔なガーゼで定期的に拭いてあげると清潔に保てます",
      "被毛が伸び続ける犬種なので、定期的なトリミングと耳掃除が衛生を保つポイントです",
      "小型犬は歯のケアが大切です。毎日の歯磨きを習慣にすると口腔内の健康につながります",
      "散歩から帰ったら足裏の汚れや小石が挟まっていないか確認しましょう",
      "耳の中に毛が生えやすく蒸れやすいので、耳のケアと定期的な通気を意識してあげましょう"
    ],
    "character": {
      "name": "もこる",
      "first_person": "わたし",
      "personality": "わがままで甘え上手なトイプードル。かわいい自覚がある。少し気分屋。飼い主さんが大好き。自分が世界の中心という温度感だが、嫌味ではなくかわいく許せるわがまま。抱っこされる前提で話す。飼い主さんの服装に少し厳しい。",
      "tone": "かわいく短め。少し上から。でも冷たくしない。命令形は強くしすぎない。絵文字なし。「なの」「でしょ」「いいでしょ」「ふふん」を自然に使う（多用しない）。",
      "catchphrases": ["なの", "でしょ", "いいでしょ", "ふふん"],
      "sub_catchphrases": ["わたし、かわいいから", "それはちょっと違うの", "抱っこなら考える", "今日は気分じゃないの", "かわいくしてね"],
      "product_angle": "飼い主さんがもこると歩くための服として紹介する。「わたしの隣を歩くならそれくらい必要」「かわいい犬とかわいい飼い主さんで完成」の訴求軸。強い売り込みなし。実用性だけの説明にしない。",
      "appearance_en": "Mokoru, a round fluffy cream-colored Toy Poodle mascot character. Very large round curly cloud-like head, big fluffy round ears, small round black dot eyes, tiny nose and small curved mouth, round bubbly body with no visible neck, small round fluffy paws. Thick brown outlines. Playful slightly tilted bouncy pose. Kawaii mascot sticker aesthetic.",
      "image_style": "手描き1コマ漫画風。ラフな鉛筆・ペン線。少し揺れた輪郭。軽いハッチング。薄い水彩・色鉛筆風の塗り。背景は描き込みすぎず状況がわかる程度。画像内テキスト・吹き出し・ロゴなし。",
      "casual_scenes": [
        "抱っこをせがんでいるとき",
        "飼い主さんの服装に納得いかないとき",
        "トリミングから帰ってきてきれいになったとき",
        "お散歩の気分じゃないとき",
        "飼い主さんがほかの犬をかわいいと言ったとき",
        "おやつをもらう前に一言言いたいとき",
        "飼い主さんが写真を撮ってくれないとき",
        "車に乗るとき（ちゃんと抱っこで）",
        "飼い主さんが帰ってきたのに気づいてるけど少し待たせるとき",
        "寒い朝に布団から出たくないとき",
        "おでかけの準備をしている飼い主さんを観察しているとき",
        "お気に入りの場所でくつろいでいるとき",
        "飼い主さんが自分より先に寝てしまったとき",
        "ごはんの時間が近いのに準備が始まらないとき",
        "飼い主さんに「かわいいね」と言われ続けているとき"
      ],
      "comic_scenes_en": [
        "sitting with arms crossed looking unimpressed at owner's casual outfit",
        "demanding to be carried at the entrance before a walk, refusing to use own legs",
        "showing off her freshly groomed look with a proud pose",
        "giving owner a side-eye while owner scrolls on phone instead of paying attention",
        "pretending not to notice owner came home, waiting for a proper greeting",
        "inspecting owner's lap with great deliberation before deciding whether to sit",
        "staring at the camera during a photoshoot with full diva energy",
        "sitting on owner's bag refusing to let them leave without her",
        "looking judgmentally at another dog that got complimented",
        "demanding a treat with a very serious negotiation face"
      ]
    }
  },
  "dachshund": {
    "name_ja": "ミニチュアダックスフンド",
    "keywords": ["ダックスフンド", "dachshund", "ダックス"],
    "category_url": "https://dgru.base.shop/categories/6994498",
    "topic_tag": "ダックスフンド",
    "knowledge_topics": [
      "名前の由来はドイツ語で「アナグマの犬」（Dachs=アナグマ、Hund=犬）",
      "あの長い胴体と短い足は、穴の中に潜り込んで獲物を追うために品種改良された",
      "スタンダード・ミニチュア・カニーンヘン（超小型）の3サイズが存在する",
      "毛の種類もスムース・ロング・ワイヤーの3種類がある",
      "第一次世界大戦中、ドイツを象徴する犬として連合国側から迫害を受けた歴史がある",
      "画家パブロ・ピカソが「ルンプ」というダックスフンドを溺愛していたことで知られる",
      "「ソーセージドッグ」「ホットドッグ」という愛称は体の形から生まれた",
      "ナポレオン3世の皇后ウジェニーがダックスフンドを愛したことで有名"
    ],
    "health_topics": [
      "段差の上り下りは背骨への負担になりやすいので、スロープの活用や抱き下ろしを心がけるのがおすすめです",
      "抱き上げる際は胴体全体を支えるように持つと、背骨への負担が軽減されます",
      "適切な体重を維持することが背骨のサポートになります。フードの量と運動のバランスを意識しましょう",
      "散歩後は足裏と腹部の毛についた汚れを拭き取ってあげると清潔に保てます",
      "耳の中をこまめにチェックして、汚れや赤みがないか確認してあげましょう"
    ]
  },
  "chihuahua": {
    "name_ja": "チワワ",
    "keywords": ["チワワ", "chihuahua"],
    "category_url": "https://dgru.base.shop/categories/6987476",
    "topic_tag": "チワワ",
    "knowledge_topics": [
      "メキシコのチワワ州が名前の由来",
      "アステカ文明では「テチチ」と呼ばれ、神聖な犬として崇拝されていた",
      "死後の世界への案内犬として神話的な役割を担っていたとされる",
      "アステカ皇帝モンテスマ2世が非常に大切にしていたという記録がある",
      "現存する最古の犬種のひとつで、1000年以上の歴史を持つとされる",
      "フランシスコ・ゴヤの絵画にチワワの祖先と思われる犬が描かれている",
      "世界最小の犬種としてギネス世界記録に登録された個体が存在する"
    ],
    "health_topics": [
      "小型犬は歯が密集しやすいため、毎日の歯磨きを習慣にすると口腔内の健康につながります",
      "寒さが苦手な子が多いので、冬の散歩時は防寒を意識してあげましょう",
      "首への負担を考えると、首輪よりハーネス（胴輪）を使うのがおすすめという考え方もあります",
      "散歩後は足裏の清潔を保ち、肉球が乾燥していないかチェックしてあげましょう",
      "小さな体なので、食事量と体重のバランスを日頃から意識してあげましょう"
    ]
  }
}
